{
  "facade-flow-mapping": [
    {
      "facade-id": "org.corda.interop/platform/tokens/v1.0",
      "facade-method-mapping": [
        {
          "facade-method": "hello",
          "flow-name": "com.r3.corda.demo.interop.tokens.workflows.interop.TokensFlow"
        },
        {
          "facade-method": "get-balance",
          "flow-name": "com.r3.corda.demo.interop.tokens.workflows.interop.TokensFlow"
        },
        {
          "facade-method": "reserve-tokens",
          "flow-name": "com.r3.corda.demo.interop.payment.workflows.interop.TokensFlow"
        }
      ]
    },
    {
      "facade-id": "org.corda.interop/platform/tokens/v2.0",
      "facade-method-mapping": [
        {
          "facade-method": "get-balance",
          "flow-name": "com.r3.corda.demo.interop.tokens.workflows.interop.TokensFlow"
        },
        {
          "facade-method": "reserve-tokens",
          "flow-name": "com.r3.corda.demo.interop.tokens.workflows.interop.TokensFlow"
        },
        {
          "facade-method": "release-reserved-tokens",
          "flow-name": "com.r3.corda.demo.interop.tokens.workflows.interop.TokensFlow"
        },
        {
          "facade-method": "spend-reserved-tokens",
          "flow-name": "com.r3.corda.demo.interop.tokens.workflows.interop.TokensFlow"
        },
        {
          "facade-method": "hello",
          "flow-name": "com.r3.corda.demo.interop.tokens.workflows.interop.TokensFlow"
        }
      ]
    }
  ]
}